{"ProjectBreakpoints":"{\"Value\":{\"System1/System1_Extract_ClientInformation.xaml\":[{\"ConditionalExpression\":null,\"ActionExpression\":null,\"ExpectedHitCounter\":null,\"ShouldContinueAfterAction\":false,\"BreakpointType\":1,\"LocationIdentifier\":\"System1_Extract_ClientInformation\",\"IsEnabled\":true,\"Annotation\":null,\"Id\":\"31f12c15-6693-4e63-acaf-01125102ec6c\",\"ActivityIdRef\":\"Sequence_1\",\"ActivityId\":\"1.1\",\"ActivityName\":\"System1_Extract_ClientInformation\",\"IsTransient\":false}]},\"CodeBreakpoints\":{}}","Compiler":"2","ProjectWatches":"{\"Value\":[]}","OpenedDocuments":"[{\"DocumentPath\":\"System1/System1_Extract_ClientInformation.xaml\",\"FactoryId\":\"{ACB8E7BA-F093-44C1-9B50-33ECA51AAE16}\"}]","ProjectActivitiesViewState":"{\"Main.xaml\":[{\"ActivityIdRef\":\"ShouldStop_1\",\"IsAdvancedOptionsExpanded\":false,\"Widgets\":{}},{\"ActivityIdRef\":\"If_3\",\"IsAdvancedOptionsExpanded\":false,\"Widgets\":{\"Then\":{\"ShowExpanded\":true},\"Else\":{\"ShowExpanded\":true}}},{\"ActivityIdRef\":\"LogMessage_1\",\"IsAdvancedOptionsExpanded\":false,\"Widgets\":{}},{\"ActivityIdRef\":\"TryCatch_2\",\"IsAdvancedOptionsExpanded\":false,\"Widgets\":{\"Try\":{\"ShowExpanded\":true},\"Finally\":{\"ShowExpanded\":true}}},{\"ActivityIdRef\":\"InvokeWorkflowFile_4\",\"IsAdvancedOptionsExpanded\":false,\"Categories\":{\"Common\":true,\"Options\":true,\"Log\":true,\"Output\":true},\"Widgets\":{}},{\"ActivityIdRef\":\"LogMessage_2\",\"IsAdvancedOptionsExpanded\":false,\"Widgets\":{}},{\"ActivityIdRef\":\"TryCatch_4\",\"IsAdvancedOptionsExpanded\":false,\"Widgets\":{\"Try\":{\"ShowExpanded\":true},\"Finally\":{\"ShowExpanded\":true}}},{\"ActivityIdRef\":\"InvokeWorkflowFile_5\",\"IsAdvancedOptionsExpanded\":false,\"Categories\":{\"Common\":true,\"Options\":true,\"Log\":true},\"Widgets\":{}},{\"ActivityIdRef\":\"TryCatch_6\",\"IsAdvancedOptionsExpanded\":false,\"Widgets\":{\"Try\":{\"ShowExpanded\":true},\"Finally\":{\"ShowExpanded\":true}}},{\"ActivityIdRef\":\"InvokeWorkflowFile_9\",\"IsAdvancedOptionsExpanded\":false,\"Categories\":{\"Common\":true,\"Options\":true,\"Log\":true},\"Widgets\":{}},{\"ActivityIdRef\":\"LogMessage_8\",\"IsAdvancedOptionsExpanded\":false,\"Widgets\":{}},{\"ActivityIdRef\":\"TryCatch_7\",\"IsAdvancedOptionsExpanded\":false,\"Widgets\":{\"Try\":{\"ShowExpanded\":true},\"Finally\":{\"ShowExpanded\":true}}},{\"ActivityIdRef\":\"InvokeWorkflowFile_10\",\"IsAdvancedOptionsExpanded\":false,\"Categories\":{\"Common\":true,\"Options\":true,\"Log\":true},\"Widgets\":{}},{\"ActivityIdRef\":\"LogMessage_9\",\"IsAdvancedOptionsExpanded\":false,\"Widgets\":{}},{\"ActivityIdRef\":\"TryCatch_8\",\"IsAdvancedOptionsExpanded\":false,\"Widgets\":{\"Try\":{\"ShowExpanded\":true},\"Finally\":{\"ShowExpanded\":true}}},{\"ActivityIdRef\":\"InvokeWorkflowFile_11\",\"IsAdvancedOptionsExpanded\":false,\"Categories\":{\"Common\":true,\"Options\":true,\"Log\":true},\"Widgets\":{}},{\"ActivityIdRef\":\"LogMessage_10\",\"IsAdvancedOptionsExpanded\":false,\"Widgets\":{}},{\"ActivityIdRef\":\"TryCatch_1\",\"IsAdvancedOptionsExpanded\":false,\"Widgets\":{\"Try\":{\"ShowExpanded\":true},\"Finally\":{\"ShowExpanded\":true}}},{\"ActivityIdRef\":\"If_1\",\"IsAdvancedOptionsExpanded\":false,\"Widgets\":{\"Then\":{\"ShowExpanded\":true},\"Else\":{\"ShowExpanded\":true}}},{\"ActivityIdRef\":\"LogMessage_14\",\"IsAdvancedOptionsExpanded\":false,\"Widgets\":{}},{\"ActivityIdRef\":\"InvokeWorkflowFile_1\",\"IsAdvancedOptionsExpanded\":false,\"Categories\":{\"Common\":true,\"Options\":true,\"Log\":true,\"Output\":true},\"Widgets\":{}},{\"ActivityIdRef\":\"If_2\",\"IsAdvancedOptionsExpanded\":false,\"Widgets\":{\"Then\":{\"ShowExpanded\":true},\"Else\":{\"ShowExpanded\":true}}},{\"ActivityIdRef\":\"If_6\",\"IsAdvancedOptionsExpanded\":false,\"Widgets\":{\"Then\":{\"ShowExpanded\":true},\"Else\":{\"ShowExpanded\":true}}},{\"ActivityIdRef\":\"InvokeWorkflowFile_2\",\"IsAdvancedOptionsExpanded\":false,\"Categories\":{\"Common\":true,\"Options\":true,\"Log\":true},\"Widgets\":{}},{\"ActivityIdRef\":\"AddLogFields_1\",\"IsAdvancedOptionsExpanded\":false,\"Widgets\":{}},{\"ActivityIdRef\":\"If_4\",\"IsAdvancedOptionsExpanded\":false,\"Widgets\":{\"Then\":{\"ShowExpanded\":true},\"Else\":{\"ShowExpanded\":true}}},{\"ActivityIdRef\":\"Throw_1\",\"IsAdvancedOptionsExpanded\":false,\"Widgets\":{}},{\"ActivityIdRef\":\"InvokeWorkflowFile_3\",\"IsAdvancedOptionsExpanded\":false,\"Categories\":{\"Common\":true,\"Options\":true,\"Log\":true},\"Widgets\":{}}],\"Framework/GetTransactionData.xaml\":[{\"ActivityIdRef\":\"LogMessage_1\",\"IsAdvancedOptionsExpanded\":false,\"Widgets\":{}},{\"ActivityIdRef\":\"TryCatch_1\",\"IsAdvancedOptionsExpanded\":false,\"Widgets\":{\"Try\":{\"ShowExpanded\":true},\"Finally\":{\"ShowExpanded\":true}}},{\"ActivityIdRef\":\"If_1\",\"IsAdvancedOptionsExpanded\":false,\"Widgets\":{\"Then\":{\"ShowExpanded\":true},\"Else\":{\"ShowExpanded\":true}}},{\"ActivityIdRef\":\"GetQueueItem_1\",\"IsAdvancedOptionsExpanded\":false,\"Categories\":{\"Options\":true,\"Output\":true},\"Widgets\":{}},{\"ActivityIdRef\":\"LogMessage_2\",\"IsAdvancedOptionsExpanded\":false,\"Widgets\":{}},{\"ActivityIdRef\":\"Rethrow_1\",\"IsAdvancedOptionsExpanded\":false,\"Widgets\":{}}],\"Framework/Process.xaml\":[{\"ActivityIdRef\":\"LogMessage_1\",\"IsAdvancedOptionsExpanded\":false,\"Widgets\":{}}],\"Framework/SetTransactionStatus.xaml\":[{\"ActivityIdRef\":\"AddLogFields_3\",\"IsAdvancedOptionsExpanded\":false,\"Widgets\":{}},{\"ActivityIdRef\":\"RemoveLogFields_3\",\"IsAdvancedOptionsExpanded\":false,\"Widgets\":{}}],\"System1/System1Login.xaml\":[{\"ActivityIdRef\":\"GetRobotCredential_3\",\"IsAdvancedOptionsExpanded\":false,\"Categories\":{\"Misc\":true,\"Output\":true},\"Widgets\":{}}],\"SHA1/Sha1.xaml\":[{\"ActivityIdRef\":\"If_1\",\"IsAdvancedOptionsExpanded\":false,\"Widgets\":{\"Then\":{\"ShowExpanded\":true},\"Else\":{\"ShowExpanded\":true}}}],\"Framework/InitAllSettings.xaml\":[{\"ActivityIdRef\":\"LogMessage_2\",\"IsAdvancedOptionsExpanded\":false,\"Widgets\":{}},{\"ActivityIdRef\":\"ForEach`1_1\",\"IsAdvancedOptionsExpanded\":false,\"Categories\":{\"\":true},\"Widgets\":{\"Body\":{\"ShowExpanded\":true}}},{\"ActivityIdRef\":\"ForEachRow_1\",\"IsAdvancedOptionsExpanded\":false,\"Categories\":{\"\":true},\"Widgets\":{\"Body\":{\"ShowExpanded\":true}}},{\"ActivityIdRef\":\"If_1\",\"IsAdvancedOptionsExpanded\":false,\"Widgets\":{\"Then\":{\"ShowExpanded\":true},\"Else\":{\"ShowExpanded\":true}}},{\"ActivityIdRef\":\"TryCatch_2\",\"IsAdvancedOptionsExpanded\":false,\"Widgets\":{\"Try\":{\"ShowExpanded\":true},\"Finally\":{\"ShowExpanded\":true}}}],\"Framework/InitAllApplications.xaml\":[{\"ActivityIdRef\":\"LogMessage_1\",\"IsAdvancedOptionsExpanded\":false,\"Widgets\":{}},{\"ActivityIdRef\":\"InvokeWorkflowFile_1\",\"IsAdvancedOptionsExpanded\":false,\"Categories\":{\"Common\":true,\"Options\":true,\"Log\":true},\"Widgets\":{}},{\"ActivityIdRef\":\"InvokeWorkflowFile_2\",\"IsAdvancedOptionsExpanded\":false,\"Categories\":{\"Common\":true,\"Options\":true,\"Log\":true},\"Widgets\":{}}],\"TestWorkflow.xaml\":[{\"ActivityIdRef\":\"InvokeWorkflowFile_1\",\"IsAdvancedOptionsExpanded\":false,\"Categories\":{\"Common\":true,\"Options\":true,\"Log\":true,\"Output\":true},\"Widgets\":{}},{\"ActivityIdRef\":\"InvokeWorkflowFile_2\",\"IsAdvancedOptionsExpanded\":false,\"Categories\":{\"Common\":true,\"Options\":true,\"Log\":true},\"Widgets\":{}}],\"System1/System1_Close.xaml\":[{\"ActivityIdRef\":\"LogMessage_2\",\"IsAdvancedOptionsExpanded\":false,\"Widgets\":{}}],\"Framework/CloseAllApplications.xaml\":[{\"ActivityIdRef\":\"LogMessage_2\",\"IsAdvancedOptionsExpanded\":false,\"Widgets\":{}},{\"ActivityIdRef\":\"InvokeWorkflowFile_1\",\"IsAdvancedOptionsExpanded\":false,\"Categories\":{\"Common\":true,\"Options\":true,\"Log\":true},\"Widgets\":{}},{\"ActivityIdRef\":\"InvokeWorkflowFile_2\",\"IsAdvancedOptionsExpanded\":false,\"Categories\":{\"Common\":true,\"Options\":true,\"Log\":true},\"Widgets\":{}}],\"SHA1/Sha1_Close.xaml\":[],\"Framework/KillAllProcesses.xaml\":[{\"ActivityIdRef\":\"LogMessage_1\",\"IsAdvancedOptionsExpanded\":false,\"Widgets\":{}},{\"ActivityIdRef\":\"KillProcess_1\",\"IsAdvancedOptionsExpanded\":false,\"Widgets\":{}},{\"ActivityIdRef\":\"TryCatch_1\",\"IsAdvancedOptionsExpanded\":false,\"Widgets\":{\"Try\":{\"ShowExpanded\":true},\"Finally\":{\"ShowExpanded\":true}}},{\"ActivityIdRef\":\"LogMessage_4\",\"IsAdvancedOptionsExpanded\":false,\"Widgets\":{}}],\"System1/System1_NavigateTo_WorkItems.xaml\":[{\"ActivityIdRef\":\"LogMessage_1\",\"IsAdvancedOptionsExpanded\":false,\"Widgets\":{}}],\"System1/System1_Extract_WlsDataTable.xaml\":[{\"ActivityIdRef\":\"OutputDataTable_1\",\"IsAdvancedOptionsExpanded\":false,\"Widgets\":{}}],\"System1/System1_Extract_ClientInformation.xaml\":[]}"}